mg_alerts/__init__.py
mg_alerts/alert_models.cpython-310-x86_64-linux-gnu.so
mg_alerts/process_manager.cpython-310-x86_64-linux-gnu.so
mg_alerts/telegram/__init__.py
mg_alerts/telegram/tg_alerts.cpython-310-x86_64-linux-gnu.so
mg_alerts/telegram/tg_base.cpython-310-x86_64-linux-gnu.so
mg_alerts/telegram/tg_config.cpython-310-x86_64-linux-gnu.so
alertswrkpi-4.4.0.dist-info/METADATA
alertswrkpi-4.4.0.dist-info/WHEEL
alertswrkpi-4.4.0.dist-info/top_level.txt
alertswrkpi-4.4.0.dist-info/RECORD
