Metadata-Version: 2.4
Name: alertswrkpi
Version: 4.4.0
Author: Kenny
Requires-Python: >=3.10
Requires-Dist: modelswrkpi
Requires-Dist: SQLAlchemy==1.*
Requires-Dist: Cython
Requires-Dist: keyrings.google.artifactregistry-auth
